Metadata-Version: 2.1
Name: cheesy-lines
Version: 1.1
Summary: cheesy lines generator
Home-page: UNKNOWN
Author: Yaswanth reddy
License: UNKNOWN
Platform: UNKNOWN
